sopaipillas/__init__.py
sopaipillas/cli.py
sopaipillas/sopaipillas.py
sopaipillas-0.2.0.dist-info/DESCRIPTION.rst
sopaipillas-0.2.0.dist-info/METADATA
sopaipillas-0.2.0.dist-info/RECORD
sopaipillas-0.2.0.dist-info/WHEEL
sopaipillas-0.2.0.dist-info/entry_points.txt
sopaipillas-0.2.0.dist-info/metadata.json
sopaipillas-0.2.0.dist-info/top_level.txt
