Metadata-Version: 2.0
Name: sopaipillas
Version: 0.2.0
Summary: Sopaipillas-making utility
Home-page: https://github.com/avenet/sopaipillas
Author: Andy Venet
Author-email: avenet@example.com
License: MIT license
Keywords: sopaipillas
Platform: UNKNOWN
Classifier: Development Status :: 2 - Pre-Alpha
Classifier: Intended Audience :: Developers
Classifier: License :: OSI Approved :: MIT License
Classifier: Natural Language :: English
Classifier: Programming Language :: Python :: 3.6
Requires-Dist: Click (>=6.0)
